mbu_rpa_core/__init__.py
mbu_rpa_core/exceptions.py
mbu_rpa_core/process_states.py
mbu_rpa_core-0.2.1.dist-info/licenses/LICENSE
mbu_rpa_core-0.2.1.dist-info/METADATA
mbu_rpa_core-0.2.1.dist-info/WHEEL
mbu_rpa_core-0.2.1.dist-info/top_level.txt
mbu_rpa_core-0.2.1.dist-info/RECORD
