Metadata-Version: 2.4
Name: mbu_rpa_core
Version: 0.2.1
Summary: Core library for RPA processes in AAK-MBU
Author-email: MBU RPA <rpa@mbu.aarhus.dk>
License: MIT
Project-URL: Repository, https://github.com/AAK-MBU/MBU-rpa-core.git
Classifier: Intended Audience :: Developers
Classifier: License :: OSI Approved :: MIT License
Classifier: Programming Language :: Python :: 3
Classifier: Programming Language :: Python :: 3.8
Classifier: Programming Language :: Python :: 3.9
Classifier: Programming Language :: Python :: 3.10
Classifier: Programming Language :: Python :: 3.11
Classifier: Operating System :: OS Independent
Requires-Python: >=3.8
License-File: LICENSE
Requires-Dist: pydantic>=2.0.0
Provides-Extra: dev
Requires-Dist: pytest>=7.0.0; extra == "dev"
Requires-Dist: pytest-cov>=4.0.0; extra == "dev"
Dynamic: license-file
